[{"coordinates": null, "createdAt": null, "dateFrom": "2023-02-25", "dateTo": null, "eventId": 4054, "firstStart": null, "id": 500, "location": "Kitzbühel", "number": 1, "shortTitle": "5. AC, ÖM Sprint Nachwuchs und Senioren", "timeFrom": null, "timeTo": null, "title": "5. AC, ÖM Sprint Nachwuchs und Senioren", "updatedAt": null}, {"coordinates": null, "createdAt": null, "dateFrom": "2023-02-25", "dateTo": null, "eventId": 4054, "firstStart": null, "id": 501, "location": "Kitzbühel", "number": 2, "shortTitle": "6. Austriacup Sprint, 1.Tirolcup", "timeFrom": null, "timeTo": null, "title": "6. Austriacup Sprint, 1.Tirolcup", "updatedAt": null}, {"coordinates": null, "createdAt": null, "dateFrom": "2023-02-26", "dateTo": null, "eventId": 4054, "firstStart": null, "id": 502, "location": "Kitzbühel", "number": 3, "shortTitle": "7. Austriacup Mittel", "timeFrom": null, "timeTo": null, "title": "7. Austriacup Mittel", "updatedAt": null}]