{"eventId": 1878, "source": "sportsoftware-html", "sourceUrl": "https://anne-cdn.oefol.at/public/legacy/event_1878_erg190217.html", "fileName": "event_1878_erg190217.html", "listType": "race", "categories": [{"name": "Mixed Elite", "declaredStarters": 11, "results": [{"name": "Zinkl, Sonja", "club": "", "timeText": "9:15", "timeS": 555, "status": "ok", "yearOfBirth": 1981}, {"name": "Varga, Stephan", "club": "", "timeText": "9:52", "timeS": 592, "status": "ok", "yearOfBirth": 2000}, {"name": "Zinkl, Sonja", "club": "", "timeText": "9:08", "timeS": 548, "status": "ok", "yearOfBirth": 1981}, {"name": "Varga, Stephan", "club": "", "timeText": "10:13", "timeS": 613, "status": "ok"}, {"name": "Zinkl, Sonja", "club": "", "timeText": "9:18", "timeS": 558, "status": "ok", "yearOfBirth": 1981}, {"name": "Varga, Stephan", "club": "", "timeText": "9:03", "timeS": 543, "status": "ok"}, {"name": "Simkovics, Anna", "club": "", "timeText": "9:10", "timeS": 550, "status": "ok", "yearOfBirth": 1993}, {"name": "Simkovics, Erik", "club": "", "timeText": "9:49", "timeS": 589, "status": "ok", "yearOfBirth": 1989}, {"name": "Simkovics, Anna", "club": "", "timeText": "9:06", "timeS": 546, "status": "ok", "yearOfBirth": 1993}, {"name": "Simkovics, Erik", "club": "", "timeText": "9:35", "timeS": 575, "status": "ok"}, {"name": "Simkovics, Anna", "club": "", "timeText": "10:04", "timeS": 604, "status": "ok", "yearOfBirth": 1993}, {"name": "Simkovics, Erik", "club": "", "timeText": "9:16", "timeS": 556, "status": "ok"}, {"name": "Lueger, Anna", "club": "", "timeText": "11:52", "timeS": 712, "status": "ok", "yearOfBirth": 2000}, {"name": "Pacher, Hannes", "club": "", "timeText": "10:38", "timeS": 638, "status": "ok", "yearOfBirth": 1959}, {"name": "Lueger, Anna", "club": "", "timeText": "10:44", "timeS": 644, "status": "ok", "yearOfBirth": 2000}, {"name": "Pacher, Hannes", "club": "", "timeText": "10:09", "timeS": 609, "status": "ok"}, {"name": "Lueger, Anna", "club": "", "timeText": "11:09", "timeS": 669, "status": "ok", "yearOfBirth": 2000}, {"name": "Pacher, Hannes", "club": "", "timeText": "9:59", "timeS": 599, "status": "ok"}, {"name": "Habenicht, Marlene", "club": "", "timeText": "10:30", "timeS": 630, "status": "ok", "yearOfBirth": 1963}, {"name": "Habenicht, Max", "club": "", "timeText": "12:55", "timeS": 775, "status": "ok", "yearOfBirth": 1991}, {"name": "Habenicht, Marlene", "club": "", "timeText": "9:55", "timeS": 595, "status": "ok", "yearOfBirth": 1963}, {"name": "Habenicht, Max", "club": "", "timeText": "11:07", "timeS": 667, "status": "ok"}, {"name": "Habenicht, Marlene", "club": "", "timeText": "9:24", "timeS": 564, "status": "ok", "yearOfBirth": 1963}, {"name": "Habenicht, Max", "club": "", "timeText": "13:50", "timeS": 830, "status": "ok"}, {"name": "Linhart, Gisa", "club": "", "timeText": "12:44", "timeS": 764, "status": "ok", "yearOfBirth": 1989}, {"name": "Kaltenbacher, Pierre", "club": "", "timeText": "10:33", "timeS": 633, "status": "ok", "yearOfBirth": 1978}, {"name": "Linhart, Gisa", "club": "", "timeText": "12:17", "timeS": 737, "status": "ok", "yearOfBirth": 1989}, {"name": "Kaltenbacher, Pierre", "club": "", "timeText": "9:15", "timeS": 555, "status": "ok"}, {"name": "Linhart, Gisa", "club": "", "timeText": "14:31", "timeS": 871, "status": "ok", "yearOfBirth": 1989}, {"name": "Kaltenbacher, Pierre", "club": "", "timeText": "9:31", "timeS": 571, "status": "ok"}, {"name": "Rogl, Franziska", "club": "", "timeText": "15:19", "timeS": 919, "status": "ok", "yearOfBirth": 1988}, {"name": "Wartbichler, Christian", "club": "", "timeText": "10:04", "timeS": 604, "status": "ok", "yearOfBirth": 1988}, {"name": "Rogl, Franziska", "club": "", "timeText": "15:21", "timeS": 921, "status": "ok", "yearOfBirth": 1988}, {"name": "Wartbichler, Christian", "club": "", "timeText": "9:40", "timeS": 580, "status": "ok"}, {"name": "Rogl, Franziska", "club": "", "timeText": "17:07", "timeS": 1027, "status": "ok", "yearOfBirth": 1988}, {"name": "Wartbichler, Christian", "club": "", "timeText": "10:02", "timeS": 602, "status": "ok"}, {"name": "Friedl, Christina", "club": "", "timeText": "29:03", "timeS": 1743, "status": "ok", "yearOfBirth": 1986}, {"name": "Hofstätter, Felix", "club": "", "timeText": "13:30", "timeS": 810, "status": "ok", "yearOfBirth": 1966}, {"name": "Friedl, Christina", "club": "", "timeText": "29:59", "timeS": 1799, "status": "ok", "yearOfBirth": 1986}, {"name": "Hofstätter, Felix", "club": "", "timeText": "12:51", "timeS": 771, "status": "ok"}, {"name": "Friedl, Christina", "club": "", "timeText": "24:36", "timeS": 1476, "status": "ok", "yearOfBirth": 1986}, {"name": "Hofstätter, Felix", "club": "", "timeText": "13:32", "timeS": 812, "status": "ok"}, {"name": "Weissova, Zuzanna", "club": "", "timeText": "11:40", "timeS": 700, "status": "ok", "yearOfBirth": 2001}, {"name": "Wickert, Adrian", "club": "", "timeText": "10:19", "timeS": 619, "status": "ok", "yearOfBirth": 2001}, {"name": "Weissova, Zuzanna", "club": "", "timeText": "10:13", "timeS": 613, "status": "ok", "yearOfBirth": 2001}, {"name": "Wickert, Adrian", "club": "", "timeText": "9:33", "timeS": 573, "status": "ok"}, {"name": "Weissova, Zuzanna", "club": "", "timeText": "9:44", "timeS": 584, "status": "ok", "yearOfBirth": 2001}, {"name": "Wickert, Adrian", "club": "", "timeText": "10:54", "timeS": 654, "status": "ok"}, {"name": "Varga, Julia", "club": "", "timeText": "12:50", "timeS": 770, "status": "ok", "yearOfBirth": 1972}, {"name": "Fesselhofer, Roland", "club": "", "timeText": "10:24", "timeS": 624, "status": "ok", "yearOfBirth": 1966}, {"name": "Varga, Julia", "club": "", "timeText": "11:25", "timeS": 685, "status": "ok", "yearOfBirth": 1972}, {"name": "Fesselhofer, Roland", "club": "", "timeText": "9:28", "timeS": 568, "status": "ok"}, {"name": "Varga, Julia", "club": "", "timeText": "10:46", "timeS": 646, "status": "ok", "yearOfBirth": 1972}, {"name": "Fesselhofer, Roland", "club": "", "timeText": "9:51", "timeS": 591, "status": "ok"}, {"name": "Hechl, Isabel", "club": "", "timeText": "10:48", "timeS": 648, "status": "ok", "yearOfBirth": 1987}, {"name": "Hölzl, Andrä", "club": "", "timeText": "10:26", "timeS": 626, "status": "ok", "yearOfBirth": 2000}, {"name": "Hechl, Isabel", "club": "", "timeText": "13:22", "timeS": 802, "status": "ok", "yearOfBirth": 1987}, {"name": "Hölzl, Andrä", "club": "", "timeText": "Fehlst", "status": "mp"}, {"name": "Hechl, Isabel", "club": "", "timeText": "14:11", "timeS": 851, "status": "ok", "yearOfBirth": 1987}, {"name": "Hölzl, Andrä", "club": "", "timeText": "10:27", "timeS": 627, "status": "ok"}, {"name": "Skern, Marina", "club": "", "timeText": "Fehlst", "status": "mp", "yearOfBirth": 1975}, {"name": "Janecek, Oldrich", "club": "", "timeText": "13:25", "timeS": 805, "status": "ok", "yearOfBirth": 1982}, {"name": "Skern, Marina", "club": "", "timeText": "15:55", "timeS": 955, "status": "ok", "yearOfBirth": 1975}, {"name": "Janecek, Oldrich", "club": "", "timeText": "12:28", "timeS": 748, "status": "ok"}, {"name": "Skern, Marina", "club": "", "timeText": "14:28", "timeS": 868, "status": "ok", "yearOfBirth": 1975}, {"name": "Janecek, Oldrich", "club": "", "timeText": "13:00", "timeS": 780, "status": "ok"}]}, {"name": "Mixed Jugend", "declaredStarters": 9, "results": [{"name": "Hnilica, Jana", "club": "", "timeText": "9:10", "timeS": 550, "status": "ok", "yearOfBirth": 2002}, {"name": "Hnilica, Hannes", "club": "", "timeText": "7:55", "timeS": 475, "status": "ok", "yearOfBirth": 2004}, {"name": "Hnilica, Jana", "club": "", "timeText": "8:02", "timeS": 482, "status": "ok"}, {"name": "Hnilica, Hannes", "club": "", "timeText": "8:42", "timeS": 522, "status": "ok"}, {"name": "Ennemoser, Lena", "club": "", "timeText": "8:23", "timeS": 503, "status": "ok"}, {"name": "Florian, Sebastian", "club": "", "timeText": "9:37", "timeS": 577, "status": "ok"}, {"name": "Ennemoser, Lena", "club": "", "timeText": "9:26", "timeS": 566, "status": "ok"}, {"name": "Florian, Sebastian", "club": "", "timeText": "10:05", "timeS": 605, "status": "ok"}, {"name": "Micko, Anja", "club": "", "timeText": "10:19", "timeS": 619, "status": "ok", "yearOfBirth": 2003}, {"name": "Micko, Tobias", "club": "", "timeText": "8:16", "timeS": 496, "status": "ok", "yearOfBirth": 2000}, {"name": "Micko, Anja", "club": "", "timeText": "13:18", "timeS": 798, "status": "ok"}, {"name": "Micko, Tobias", "club": "", "timeText": "7:08", "timeS": 428, "status": "ok"}, {"name": "Moosmann, Lisa", "club": "", "timeText": "8:49", "timeS": 529, "status": "ok", "yearOfBirth": 2002}, {"name": "Moosmann, Felix", "club": "", "timeText": "10:50", "timeS": 650, "status": "ok", "yearOfBirth": 2002}, {"name": "Moosmann, Lisa", "club": "", "timeText": "10:16", "timeS": 616, "status": "ok"}, {"name": "Moosmann, Felix", "club": "", "timeText": "12:28", "timeS": 748, "status": "ok"}, {"name": "Posch, Elisa", "club": "", "timeText": "12:01", "timeS": 721, "status": "ok", "yearOfBirth": 1998}, {"name": "Perktold, Benedikt", "club": "", "timeText": "13:14", "timeS": 794, "status": "ok", "yearOfBirth": 1950}, {"name": "Posch, Elisa", "club": "", "timeText": "14:20", "timeS": 860, "status": "ok"}, {"name": "Perktold, Benedikt", "club": "", "timeText": "10:15", "timeS": 615, "status": "ok"}, {"name": "Huter, Katharina", "club": "", "timeText": "14:49", "timeS": 889, "status": "ok", "yearOfBirth": 2001}, {"name": "Schnegg, Leo", "club": "", "timeText": "13:24", "timeS": 804, "status": "ok", "yearOfBirth": 2001}, {"name": "Huter, Katharina", "club": "", "timeText": "16:56", "timeS": 1016, "status": "ok"}, {"name": "Schnegg, Leo", "club": "", "timeText": "9:59", "timeS": 599, "status": "ok"}, {"name": "Florian, Anika", "club": "", "timeText": "14:49", "timeS": 889, "status": "ok", "yearOfBirth": 1975}, {"name": "Pupeter, Xaver", "club": "", "timeText": "12:59", "timeS": 779, "status": "ok", "yearOfBirth": 1970}, {"name": "Florian, Anika", "club": "", "timeText": "17:26", "timeS": 1046, "status": "ok"}, {"name": "Pupeter, Xaver", "club": "", "timeText": "12:04", "timeS": 724, "status": "ok"}, {"name": "Ennemoser, Lisa", "club": "", "timeText": "9:44", "timeS": 584, "status": "ok", "yearOfBirth": 1969}, {"name": "Veseley, Teresa", "club": "", "timeText": "8:46", "timeS": 526, "status": "ok", "yearOfBirth": 1966}, {"name": "Ennemoser, Lisa", "club": "", "timeText": "10:42", "timeS": 642, "status": "ok"}, {"name": "Veseley, Teresa", "club": "", "timeText": "10:00", "timeS": 600, "status": "ok"}, {"name": "Rass, Maximilian", "club": "", "timeText": "19:45", "timeS": 1185, "status": "ok", "yearOfBirth": 1995}, {"name": "Heumader, Aaron", "club": "", "timeText": "30:53", "timeS": 1853, "status": "ok", "yearOfBirth": 2001}, {"name": "Rass, Maximilian", "club": "", "timeText": "17:34", "timeS": 1054, "status": "ok"}, {"name": "Heumader, Aaron", "club": "", "timeText": "Aufg", "status": "dnf"}]}, {"name": "Mixed Masters", "declaredStarters": 15, "results": [{"name": "Habenicht, Regina", "club": "", "timeText": "10:18", "timeS": 618, "status": "ok", "yearOfBirth": 1963}, {"name": "Mandl, Robert", "club": "", "timeText": "10:39", "timeS": 639, "status": "ok", "yearOfBirth": 1962}, {"name": "Habenicht, Regina", "club": "", "timeText": "8:39", "timeS": 519, "status": "ok"}, {"name": "Mandl, Robert", "club": "", "timeText": "9:32", "timeS": 572, "status": "ok"}, {"name": "Hnilica, Sonja", "club": "", "timeText": "12:16", "timeS": 736, "status": "ok", "yearOfBirth": 1968}, {"name": "Hnilica, Thomas", "club": "", "timeText": "9:32", "timeS": 572, "status": "ok", "yearOfBirth": 1968}, {"name": "Hnilica, Sonja", "club": "", "timeText": "12:31", "timeS": 751, "status": "ok"}, {"name": "Hnilica, Thomas", "club": "", "timeText": "9:15", "timeS": 555, "status": "ok"}, {"name": "Finder, Gaby", "club": "", "timeText": "12:33", "timeS": 753, "status": "ok", "yearOfBirth": 1965}, {"name": "Poell, Matthias", "club": "", "timeText": "10:36", "timeS": 636, "status": "ok", "yearOfBirth": 1972}, {"name": "Finder, Gaby", "club": "", "timeText": "11:21", "timeS": 681, "status": "ok"}, {"name": "Poell, Matthias", "club": "", "timeText": "9:59", "timeS": 599, "status": "ok"}, {"name": "Micko, Roswitha", "club": "", "timeText": "14:35", "timeS": 875, "status": "ok", "yearOfBirth": 1965}, {"name": "Kramer, Klaus", "club": "", "timeText": "9:38", "timeS": 578, "status": "ok", "yearOfBirth": 1965}, {"name": "Micko, Roswitha", "club": "", "timeText": "12:30", "timeS": 750, "status": "ok"}, {"name": "Kramer, Klaus", "club": "", "timeText": "9:17", "timeS": 557, "status": "ok"}, {"name": "Walch, Karin", "club": "", "timeText": "12:50", "timeS": 770, "status": "ok", "yearOfBirth": 1964}, {"name": "Kradischnig, Günter", "club": "", "timeText": "10:39", "timeS": 639, "status": "ok", "yearOfBirth": 1961}, {"name": "Walch, Karin", "club": "", "timeText": "13:36", "timeS": 816, "status": "ok"}, {"name": "Kradischnig, Günter", "club": "", "timeText": "10:19", "timeS": 619, "status": "ok"}, {"name": "Adenstedt, Barbara", "club": "", "timeText": "12:12", "timeS": 732, "status": "ok", "yearOfBirth": 1967}, {"name": "Adenstedt, Erik", "club": "", "timeText": "11:47", "timeS": 707, "status": "ok", "yearOfBirth": 1969}, {"name": "Adenstedt, Barbara", "club": "", "timeText": "13:04", "timeS": 784, "status": "ok"}, {"name": "Adenstedt, Erik", "club": "", "timeText": "11:39", "timeS": 699, "status": "ok"}, {"name": "Gollmann, Birgit", "club": "", "timeText": "14:46", "timeS": 886, "status": "ok", "yearOfBirth": 1964}, {"name": "Zapletal, Josef", "club": "", "timeText": "11:01", "timeS": 661, "status": "ok", "yearOfBirth": 1959}, {"name": "Gollmann, Birgit", "club": "", "timeText": "13:49", "timeS": 829, "status": "ok"}, {"name": "Zapletal, Josef", "club": "", "timeText": "9:50", "timeS": 590, "status": "ok"}, {"name": "Lugsteiner, Karin", "club": "", "timeText": "13:42", "timeS": 822, "status": "ok", "yearOfBirth": 1957}, {"name": "Gratzer, Hans Georg", "club": "", "timeText": "13:09", "timeS": 789, "status": "ok", "yearOfBirth": 1956}, {"name": "Lugsteiner, Karin", "club": "", "timeText": "13:04", "timeS": 784, "status": "ok"}, {"name": "Gratzer, Hans Georg", "club": "", "timeText": "11:45", "timeS": 705, "status": "ok"}, {"name": "Erhart, Andrea", "club": "", "timeText": "13:08", "timeS": 788, "status": "ok", "yearOfBirth": 1968}, {"name": "Erhart, Herbert", "club": "", "timeText": "14:27", "timeS": 867, "status": "ok", "yearOfBirth": 1965}, {"name": "Erhart, Andrea", "club": "", "timeText": "13:49", "timeS": 829, "status": "ok"}, {"name": "Erhart, Herbert", "club": "", "timeText": "13:48", "timeS": 828, "status": "ok"}, {"name": "Glatz, Sylvia", "club": "", "timeText": "13:22", "timeS": 802, "status": "ok", "yearOfBirth": 1967}, {"name": "Glatz, Ewald", "club": "", "timeText": "16:09", "timeS": 969, "status": "ok", "yearOfBirth": 1967}, {"name": "Glatz, Sylvia", "club": "", "timeText": "14:10", "timeS": 850, "status": "ok"}, {"name": "Glatz, Ewald", "club": "", "timeText": "13:42", "timeS": 822, "status": "ok"}, {"name": "Kirchmeir, Elisabeth", "club": "", "timeText": "14:58", "timeS": 898, "status": "ok", "yearOfBirth": 1966}, {"name": "Lipphart-Kirchmeir, Harald", "club": "", "timeText": "15:10", "timeS": 910, "status": "ok", "yearOfBirth": 1967}, {"name": "Kirchmeir, Elisabeth", "club": "", "timeText": "13:37", "timeS": 817, "status": "ok"}, {"name": "Lipphart-Kirchmeir, Harald", "club": "", "timeText": "15:58", "timeS": 958, "status": "ok"}, {"name": "Berger, Gislind", "club": "", "timeText": "13:11", "timeS": 791, "status": "ok", "yearOfBirth": 1966}, {"name": "Kaminger, Ingrid", "club": "", "timeText": "20:13", "timeS": 1213, "status": "ok", "yearOfBirth": 1969}, {"name": "Berger, Gislind", "club": "", "timeText": "14:40", "timeS": 880, "status": "ok"}, {"name": "Kaminger, Ingrid", "club": "", "timeText": "17:14", "timeS": 1034, "status": "ok"}, {"name": "Zeiner, Elisabeth", "club": "", "timeText": "12:56", "timeS": 776, "status": "ok", "yearOfBirth": 1965}, {"name": "Zeiner, Harald", "club": "", "timeText": "16:35", "timeS": 995, "status": "ok", "yearOfBirth": 1964}, {"name": "Zeiner, Elisabeth", "club": "", "timeText": "24:15", "timeS": 1455, "status": "ok"}, {"name": "Zeiner, Harald", "club": "", "timeText": "12:58", "timeS": 778, "status": "ok"}, {"name": "Lueger, Ingrid", "club": "", "timeText": "Fehlst", "status": "mp", "yearOfBirth": 1968}, {"name": "Lueger, Reinhold", "club": "", "timeText": "20:59", "timeS": 1259, "status": "ok", "yearOfBirth": 1966}, {"name": "Lueger, Ingrid", "club": "", "timeText": "16:22", "timeS": 982, "status": "ok"}, {"name": "Lueger, Reinhold", "club": "", "timeText": "15:01", "timeS": 901, "status": "ok"}, {"name": "Lassl, Christa", "club": "", "timeText": "Fehlst", "status": "mp", "yearOfBirth": 1962}, {"name": "Hochwarter, Rudolf", "club": "", "timeText": "12:50", "timeS": 770, "status": "ok", "yearOfBirth": 1956}, {"name": "Lassl, Christa", "club": "", "timeText": "14:13", "timeS": 853, "status": "ok"}, {"name": "Hochwarter, Rudolf", "club": "", "timeText": "12:35", "timeS": 755, "status": "ok"}]}, {"name": "Mixed Offen", "declaredStarters": 7, "results": [{"name": "Plohn, Markus", "club": "", "timeText": "10:10", "timeS": 610, "status": "ok", "yearOfBirth": 1987}, {"name": "Stockmayer, Michael", "club": "", "timeText": "9:53", "timeS": 593, "status": "ok", "yearOfBirth": 1968}, {"name": "Plohn, Markus", "club": "", "timeText": "10:42", "timeS": 642, "status": "ok"}, {"name": "Stockmayer, Michael", "club": "", "timeText": "8:56", "timeS": 536, "status": "ok"}, {"name": "Kiacz, Bence", "club": "", "timeText": "10:04", "timeS": 604, "status": "ok"}, {"name": "Janko, Tamas", "club": "", "timeText": "10:18", "timeS": 618, "status": "ok"}, {"name": "Kiacz, Bence", "club": "", "timeText": "10:57", "timeS": 657, "status": "ok"}, {"name": "Janko, Tamas", "club": "", "timeText": "10:37", "timeS": 637, "status": "ok"}, {"name": "Schimpl, Peter", "club": "", "timeText": "13:42", "timeS": 822, "status": "ok", "yearOfBirth": 1993}, {"name": "Bürger, Jörg", "club": "", "timeText": "10:42", "timeS": 642, "status": "ok", "yearOfBirth": 1962}, {"name": "Schimpl, Peter", "club": "", "timeText": "11:09", "timeS": 669, "status": "ok"}, {"name": "Bürger, Jörg", "club": "", "timeText": "9:11", "timeS": 551, "status": "ok"}, {"name": "Dobnik, Elias", "club": "", "timeText": "14:18", "timeS": 858, "status": "ok", "yearOfBirth": 2002}, {"name": "Dobnik, Günther", "club": "", "timeText": "10:32", "timeS": 632, "status": "ok", "yearOfBirth": 1955}, {"name": "Dobnik, Elias", "club": "", "timeText": "12:20", "timeS": 740, "status": "ok"}, {"name": "Dobnik, Günther", "club": "", "timeText": "11:20", "timeS": 680, "status": "ok"}, {"name": "Erhart, Antonia", "club": "", "timeText": "9:49", "timeS": 589, "status": "ok"}, {"name": "Walch, Christian", "club": "", "timeText": "14:47", "timeS": 887, "status": "ok"}, {"name": "Erhart, Antonia", "club": "", "timeText": "10:09", "timeS": 609, "status": "ok"}, {"name": "Walch, Christian", "club": "", "timeText": "13:49", "timeS": 829, "status": "ok"}, {"name": "Satrapa, Vito", "club": "", "timeText": "9:43", "timeS": 583, "status": "ok"}, {"name": "Mayer, Andreas", "club": "", "timeText": "20:06", "timeS": 1206, "status": "ok"}, {"name": "Satrapa, Vito", "club": "", "timeText": "9:03", "timeS": 543, "status": "ok"}, {"name": "Mayer, Andreas", "club": "", "timeText": "17:55", "timeS": 1075, "status": "ok"}, {"name": "Kogler, Martina", "club": "", "timeText": "11:51", "timeS": 711, "status": "ok"}, {"name": "Hechl, Georg", "club": "", "timeText": "16:50", "timeS": 1010, "status": "ok", "yearOfBirth": 1951}, {"name": "Kogler, Martina", "club": "", "timeText": "Fehlst", "status": "mp"}]}]}